Workbook

Sheet Samenvatting
A1: Cashflow Uyar Web & Trade
A2: Revolut Business | periode 10 mei t/m 24 juni 2026 | alle bedragen in EUR
A4: Totaal binnengekomen (alle inkomsten) | B4: =SUM(Transacties!L:L)
A5: waarvan omzet (Stripe + Mollie) | B5: =SUMIF(Transacties!H:H,"Omzet",Transacties!L:L)
A6: waarvan eigen inleg (jij stort terug) | B6: =SUMIF(Transacties!H:H,"Eigen inleg",Transacties!L:L)
A8: Totaal eruit (alle uitgaven) | B8: =SUM(Transacties!K:K)
A9: waarvan zakelijk | B9: =SUMIF(Transacties!I:I,"Zakelijk",Transacties!K:K)
A10: waarvan prive (door jou te dragen) | B10: =SUMIF(Transacties!I:I,"Prive",Transacties!K:K)
A12: Netto kasstroom (in - uit) | B12: =B4-B8
A14: PRIVE TERUG TE BETALEN AAN HET BEDRIJF
A15: Prive uitgaven + opnames van zakelijke rekening | B15: =SUMIF(Transacties!I:I,"Prive",Transacties!K:K)
A16: Al teruggestort (eigen inleg) | B16: =SUMIF(Transacties!H:H,"Eigen inleg",Transacties!L:L)
A17: NOG TERUG TE BETALEN | B17: =B15-B16
A19: Controle met Revolut-statement (moet kloppen):
A20: Statement: Money in 102.382,04 / Money out 93.727,99
A21: Lees tabblad 'Toelichting' voor uitleg + de aannames.

Sheet Transacties
A1: Datum | B1: Week nr | C1: Week-start | D1: Maand | E1: Richting | F1: Omschrijving | G1: Tegenpartij | H1: Categorie | I1: Prive/Zakelijk | J1: Terugbetalen | K1: Bedrag uit (€) | L1: Bedrag in (€) | M1: Origineel (valuta) | N1: Notitie
A2: 46197 | B2: =ISOWEEKNUM(A2) | C2: =A2-WEEKDAY(A2,2)+1 | D2: =TEXT(A2,"mmm yyyy") | E2: Uit | F2: Easyparknlcom | G2: Easypark | H2: Parkeren | I2: Prive | J2: Ja | K2: 3.21
A3: 46197 | B3: =ISOWEEKNUM(A3) | C3: =A3-WEEKDAY(A3,2)+1 | D3: =TEXT(A3,"mmm yyyy") | E3: In | F3: Money added Stripe A5P0M0 | G3: Stripe | H3: Omzet | I3: Zakelijk | J3: Nee | L3: 1182.57
A4: 46196 | B4: =ISOWEEKNUM(A4) | C4: =A4-WEEKDAY(A4,2)+1 | D4: =TEXT(A4,"mmm yyyy") | E4: Uit | F4: Vercel Inc. | G4: Vercel | H4: Software & Tools | I4: Zakelijk | J4: Nee | K4: 21.19 | M4: $24.20
A5: 46196 | B5: =ISOWEEKNUM(A5) | C5: =A5-WEEKDAY(A5,2)+1 | D5: =TEXT(A5,"mmm yyyy") | E5: Uit | F5: Paypal it Service | G5: PayPal | H5: Software & Tools | I5: Zakelijk | J5: Nee | K5: 2.61 | M5: $2.99
A6: 46196 | B6: =ISOWEEKNUM(A6) | C6: =A6-WEEKDAY(A6,2)+1 | D6: =TEXT(A6,"mmm yyyy") | E6: Uit | F6: Commentguard.io | G6: Commentguard | H6: Software & Tools | I6: Zakelijk | J6: Nee | K6: 30.63 | M6: $35.09
A7: 46196 | B7: =ISOWEEKNUM(A7) | C7: =A7-WEEKDAY(A7,2)+1 | D7: =TEXT(A7,"mmm yyyy") | E7: In | F7: Money added Stripe T0T0P4 | G7: Stripe | H7: Omzet | I7: Zakelijk | J7: Nee | L7: 1684.8
A8: 46196 | B8: =ISOWEEKNUM(A8) | C8: =A8-WEEKDAY(A8,2)+1 | D8: =TEXT(A8,"mmm yyyy") | E8: Uit | F8: To HK Jinchenyun CD000749 | G8: HK Jinchenyun | H8: Voorraad/Leverancier | I8: Zakelijk | J8: Nee | K8: 8000.2 | N8: incl. 0.20 fee
A9: 46196 | B9: =ISOWEEKNUM(A9) | C9: =A9-WEEKDAY(A9,2)+1 | D9: =TEXT(A9,"mmm yyyy") | E9: Uit | F9: To Hiltermann Lease B.V. | G9: Hiltermann Lease | H9: Auto/Lease | I9: Zakelijk | J9: Nee | K9: 1779.5 | N9: Leasecontract - check prive/bijtelling
A10: 46195 | B10: =ISOWEEKNUM(A10) | C10: =A10-WEEKDAY(A10,2)+1 | D10: =TEXT(A10,"mmm yyyy") | E10: Uit | F10: Checkify.pro | G10: Checkify.pro | H10: Software & Tools | I10: Zakelijk | J10: Nee | K10: 37.07
A11: 46195 | B11: =ISOWEEKNUM(A11) | C11: =A11-WEEKDAY(A11,2)+1 | D11: =TEXT(A11,"mmm yyyy") | E11: Uit | F11: Easyparknlcom | G11: Easypark | H11: Parkeren | I11: Prive | J11: Ja | K11: 3.27
A12: 46195 | B12: =ISOWEEKNUM(A12) | C12: =A12-WEEKDAY(A12,2)+1 | D12: =TEXT(A12,"mmm yyyy") | E12: Uit | F12: Apple.com/bill | G12: Apple | H12: Software & Tools | I12: Zakelijk | J12: Nee | K12: 10 | N12: Check prive
A13: 46195 | B13: =ISOWEEKNUM(A13) | C13: =A13-WEEKDAY(A13,2)+1 | D13: =TEXT(A13,"mmm yyyy") | E13: In | F13: Money added Stripe Q8Y0Z5 | G13: Stripe | H13: Omzet | I13: Zakelijk | J13: Nee | L13: 2645.68
A14: 46194 | B14: =ISOWEEKNUM(A14) | C14: =A14-WEEKDAY(A14,2)+1 | D14: =TEXT(A14,"mmm yyyy") | E14: Uit | F14: To CC Ecommerce 0722 | G14: CC Ecommerce Solutions | H14: Voorraad/Leverancier | I14: Zakelijk | J14: Nee | K14: 2600.2 | N14: incl. fee
A15: 46194 | B15: =ISOWEEKNUM(A15) | C15: =A15-WEEKDAY(A15,2)+1 | D15: =TEXT(A15,"mmm yyyy") | E15: Uit | F15: Checkify.pro Subs Fees | G15: Checkify.pro | H15: Software & Tools | I15: Zakelijk | J15: Nee | K15: 50.42
A16: 46194 | B16: =ISOWEEKNUM(A16) | C16: =A16-WEEKDAY(A16,2)+1 | D16: =TEXT(A16,"mmm yyyy") | E16: Uit | F16: Dhgate.com | G16: DHgate | H16: Voorraad/Leverancier | I16: Zakelijk | J16: Nee | K16: 26.61
A17: 46193 | B17: =ISOWEEKNUM(A17) | C17: =A17-WEEKDAY(A17,2)+1 | D17: =TEXT(A17,"mmm yyyy") | E17: Uit | F17: Klaviyo Inc Software | G17: Klaviyo | H17: Software & Tools | I17: Zakelijk | J17: Nee | K17: 26.44 | M17: $30.00
A18: 46193 | B18: =ISOWEEKNUM(A18) | C18: =A18-WEEKDAY(A18,2)+1 | D18: =TEXT(A18,"mmm yyyy") | E18: Uit | F18: Oxylabs | G18: Oxylabs | H18: Software & Tools | I18: Zakelijk | J18: Nee | K18: 31.69 | M18: $36.30
A19: 46193 | B19: =ISOWEEKNUM(A19) | C19: =A19-WEEKDAY(A19,2)+1 | D19: =TEXT(A19,"mmm yyyy") | E19: Uit | F19: Easyparknlcom | G19: Easypark | H19: Parkeren | I19: Prive | J19: Ja | K19: 3.27
A20: 46193 | B20: =ISOWEEKNUM(A20) | C20: =A20-WEEKDAY(A20,2)+1 | D20: =TEXT(A20,"mmm yyyy") | E20: Uit | F20: Makara Amsterdam-west | G20: Makara | H20: Eten & Restaurant | I20: Prive | J20: Ja | K20: 40 | N20: Restaurant
A21: 46193 | B21: =ISOWEEKNUM(A21) | C21: =A21-WEEKDAY(A21,2)+1 | D21: =TEXT(A21,"mmm yyyy") | E21: Uit | F21: Shopify 546518278 | G21: Shopify | H21: Software & Tools | I21: Zakelijk | J21: Nee | K21: 69.67
A22: 46193 | B22: =ISOWEEKNUM(A22) | C22: =A22-WEEKDAY(A22,2)+1 | D22: =TEXT(A22,"mmm yyyy") | E22: Uit | F22: Dm Drogerie Sagt Danke | G22: DM Drogerie | H22: Persoonlijk | I22: Prive | J22: Ja | K22: 24.2 | N22: Drogist (DE)
A23: 46192 | B23: =ISOWEEKNUM(A23) | C23: =A23-WEEKDAY(A23,2)+1 | D23: =TEXT(A23,"mmm yyyy") | E23: Uit | F23: Haus Des Doeners | G23: Haus Des Doeners | H23: Eten & Restaurant | I23: Prive | J23: Ja | K23: 20.5
A24: 46192 | B24: =ISOWEEKNUM(A24) | C24: =A24-WEEKDAY(A24,2)+1 | D24: =TEXT(A24,"mmm yyyy") | E24: Uit | F24: Tamoil Enschede | G24: Tamoil | H24: Brandstof | I24: Prive | J24: Ja | K24: 24.99
A25: 46192 | B25: =ISOWEEKNUM(A25) | C25: =A25-WEEKDAY(A25,2)+1 | D25: =TEXT(A25,"mmm yyyy") | E25: Uit | F25: Bck varo Energy Retail B. | G25: Varo Energy | H25: Brandstof | I25: Prive | J25: Ja | K25: 1
A26: 46192 | B26: =ISOWEEKNUM(A26) | C26: =A26-WEEKDAY(A26,2)+1 | D26: =TEXT(A26,"mmm yyyy") | E26: Uit | F26: Bp De Bolder | G26: Bp De Bolder | H26: Eten & Restaurant | I26: Prive | J26: Ja | K26: 12.02
A27: 46192 | B27: =ISOWEEKNUM(A27) | C27: =A27-WEEKDAY(A27,2)+1 | D27: =TEXT(A27,"mmm yyyy") | E27: Uit | F27: Flughafen Duesseldorf | G27: Flughafen Dusseldorf | H27: Parkeren | I27: Prive | J27: Ja | K27: 8 | N27: Luchthaven (parkeren/reizen)
A28: 46192 | B28: =ISOWEEKNUM(A28) | C28: =A28-WEEKDAY(A28,2)+1 | D28: =TEXT(A28,"mmm yyyy") | E28: Uit | F28: Shell Express Hilversum N | G28: Shell | H28: Brandstof | I28: Prive | J28: Ja | K28: 20.1
A29: 46192 | B29: =ISOWEEKNUM(A29) | C29: =A29-WEEKDAY(A29,2)+1 | D29: =TEXT(A29,"mmm yyyy") | E29: Uit | F29: Cafe Femm | G29: Cafe Femm | H29: Eten & Restaurant | I29: Prive | J29: Ja | K29: 14.9
A30: 46192 | B30: =ISOWEEKNUM(A30) | C30: =A30-WEEKDAY(A30,2)+1 | D30: =TEXT(A30,"mmm yyyy") | E30: Uit | F30: Acs 05854834 Odido | G30: Odido | H30: Telefoon/Communicatie | I30: Zakelijk | J30: Nee | K30: 10 | N30: Telefoon - check prive
A31: 46192 | B31: =ISOWEEKNUM(A31) | C31: =A31-WEEKDAY(A31,2)+1 | D31: =TEXT(A31,"mmm yyyy") | E31: In | F31: Money added Stripe T3H9S1 | G31: Stripe | H31: Omzet | I31: Zakelijk | J31: Nee | L31: 2558.93
A32: 46191 | B32: =ISOWEEKNUM(A32) | C32: =A32-WEEKDAY(A32,2)+1 | D32: =TEXT(A32,"mmm yyyy") | E32: Uit | F32: Esso Maartensdijk Ni | G32: Esso | H32: Brandstof | I32: Prive | J32: Ja | K32: 5
A33: 46191 | B33: =ISOWEEKNUM(A33) | C33: =A33-WEEKDAY(A33,2)+1 | D33: =TEXT(A33,"mmm yyyy") | E33: Uit | F33: Bck roebert Tankstations | G33: Roebert Tankstations | H33: Brandstof | I33: Prive | J33: Ja | K33: 5
A34: 46191 | B34: =ISOWEEKNUM(A34) | C34: =A34-WEEKDAY(A34,2)+1 | D34: =TEXT(A34,"mmm yyyy") | E34: Uit | F34: Mm Leidsche Rijn | G34: MM Leidsche Rijn | H34: Boodschappen | I34: Prive | J34: Ja | K34: 32.89 | N34: Verifieer
A35: 46191 | B35: =ISOWEEKNUM(A35) | C35: =A35-WEEKDAY(A35,2)+1 | D35: =TEXT(A35,"mmm yyyy") | E35: Uit | F35: Easyparknlcom | G35: Easypark | H35: Parkeren | I35: Prive | J35: Ja | K35: 1.66
A36: 46191 | B36: =ISOWEEKNUM(A36) | C36: =A36-WEEKDAY(A36,2)+1 | D36: =TEXT(A36,"mmm yyyy") | E36: Uit | F36: To Talat Uyar Prive | G36: Talat (prive) | H36: Prive-opname | I36: Prive | J36: Ja | K36: 166
A37: 46191 | B37: =ISOWEEKNUM(A37) | C37: =A37-WEEKDAY(A37,2)+1 | D37: =TEXT(A37,"mmm yyyy") | E37: In | F37: Money added Stripe S4J5K4 | G37: Stripe | H37: Omzet | I37: Zakelijk | J37: Nee | L37: 8812.14
A38: 46191 | B38: =ISOWEEKNUM(A38) | C38: =A38-WEEKDAY(A38,2)+1 | D38: =TEXT(A38,"mmm yyyy") | E38: Uit | F38: To Goatly VITAL NAD+ via Stripe | G38: Goatly | H38: Overig | I38: Zakelijk | J38: Nee | K38: 23.97 | N38: Goatly/NAD+ - verifieer
A39: 46190 | B39: =ISOWEEKNUM(A39) | C39: =A39-WEEKDAY(A39,2)+1 | D39: =TEXT(A39,"mmm yyyy") | E39: Uit | F39: Railway | G39: Railway | H39: Software & Tools | I39: Zakelijk | J39: Nee | K39: 4.31 | M39: $5.00 | N39: Hosting/infra
A40: 46190 | B40: =ISOWEEKNUM(A40) | C40: =A40-WEEKDAY(A40,2)+1 | D40: =TEXT(A40,"mmm yyyy") | E40: Uit | F40: Albert Heijn 1155 | G40: Albert Heijn | H40: Boodschappen | I40: Prive | J40: Ja | K40: 12.4
A41: 46190 | B41: =ISOWEEKNUM(A41) | C41: =A41-WEEKDAY(A41,2)+1 | D41: =TEXT(A41,"mmm yyyy") | E41: Uit | F41: Checkify.pro Subs Fees | G41: Checkify.pro | H41: Software & Tools | I41: Zakelijk | J41: Nee | K41: 25.19
A42: 46190 | B42: =ISOWEEKNUM(A42) | C42: =A42-WEEKDAY(A42,2)+1 | D42: =TEXT(A42,"mmm yyyy") | E42: Uit | F42: Kindle Svcs | G42: Amazon Kindle | H42: Persoonlijk | I42: Prive | J42: Ja | K42: 0.99
A43: 46190 | B43: =ISOWEEKNUM(A43) | C43: =A43-WEEKDAY(A43,2)+1 | D43: =TEXT(A43,"mmm yyyy") | E43: In | F43: Money added Stripe R6O9G3 | G43: Stripe | H43: Omzet | I43: Zakelijk | J43: Nee | L43: 2579.12
A44: 46190 | B44: =ISOWEEKNUM(A44) | C44: =A44-WEEKDAY(A44,2)+1 | D44: =TEXT(A44,"mmm yyyy") | E44: Uit | F44: To CC Ecommerce 0722 | G44: CC Ecommerce Solutions | H44: Voorraad/Leverancier | I44: Zakelijk | J44: Nee | K44: 2000
A45: 46190 | B45: =ISOWEEKNUM(A45) | C45: =A45-WEEKDAY(A45,2)+1 | D45: =TEXT(A45,"mmm yyyy") | E45: Uit | F45: To Uyar Web & Trade Test | G45: eigen rekening | H45: Overig | I45: Zakelijk | J45: Nee | K45: 10 | N45: Interne overboeking / test
A46: 46189 | B46: =ISOWEEKNUM(A46) | C46: =A46-WEEKDAY(A46,2)+1 | D46: =TEXT(A46,"mmm yyyy") | E46: Uit | F46: Albert Heijn 1155 | G46: Albert Heijn | H46: Boodschappen | I46: Prive | J46: Ja | K46: 3.28
A47: 46189 | B47: =ISOWEEKNUM(A47) | C47: =A47-WEEKDAY(A47,2)+1 | D47: =TEXT(A47,"mmm yyyy") | E47: Uit | F47: Nyx vendingland | G47: Vendingland | H47: Eten & Restaurant | I47: Prive | J47: Ja | K47: 2.8 | N47: Automaat
A48: 46189 | B48: =ISOWEEKNUM(A48) | C48: =A48-WEEKDAY(A48,2)+1 | D48: =TEXT(A48,"mmm yyyy") | E48: In | F48: Money added Stripe B6L0P2 | G48: Stripe | H48: Omzet | I48: Zakelijk | J48: Nee | L48: 3622.3
A49: 46188 | B49: =ISOWEEKNUM(A49) | C49: =A49-WEEKDAY(A49,2)+1 | D49: =TEXT(A49,"mmm yyyy") | E49: Uit | F49: To CC Ecommerce 0722 | G49: CC Ecommerce Solutions | H49: Voorraad/Leverancier | I49: Zakelijk | J49: Nee | K49: 3000
A50: 46188 | B50: =ISOWEEKNUM(A50) | C50: =A50-WEEKDAY(A50,2)+1 | D50: =TEXT(A50,"mmm yyyy") | E50: Uit | F50: Checkify.pro | G50: Checkify.pro | H50: Software & Tools | I50: Zakelijk | J50: Nee | K50: 43.37
A51: 46188 | B51: =ISOWEEKNUM(A51) | C51: =A51-WEEKDAY(A51,2)+1 | D51: =TEXT(A51,"mmm yyyy") | E51: Uit | F51: Bck cigkoftem 053 | G51: Cigkoftem | H51: Eten & Restaurant | I51: Prive | J51: Ja | K51: 5.95
A52: 46188 | B52: =ISOWEEKNUM(A52) | C52: =A52-WEEKDAY(A52,2)+1 | D52: =TEXT(A52,"mmm yyyy") | E52: Uit | F52: Albert Heijn 2325 | G52: Albert Heijn | H52: Boodschappen | I52: Prive | J52: Ja | K52: 1.98
A53: 46188 | B53: =ISOWEEKNUM(A53) | C53: =A53-WEEKDAY(A53,2)+1 | D53: =TEXT(A53,"mmm yyyy") | E53: Uit | F53: Bp De Bolder | G53: Bp De Bolder | H53: Eten & Restaurant | I53: Prive | J53: Ja | K53: 4.95
A54: 46188 | B54: =ISOWEEKNUM(A54) | C54: =A54-WEEKDAY(A54,2)+1 | D54: =TEXT(A54,"mmm yyyy") | E54: Uit | F54: Ok Enschede Bl | G54: OK Tankstation | H54: Brandstof | I54: Prive | J54: Ja | K54: 3.1
A55: 46188 | B55: =ISOWEEKNUM(A55) | C55: =A55-WEEKDAY(A55,2)+1 | D55: =TEXT(A55,"mmm yyyy") | E55: Uit | F55: Easyparknlcom | G55: Easypark | H55: Parkeren | I55: Prive | J55: Ja | K55: 1.86
A56: 46188 | B56: =ISOWEEKNUM(A56) | C56: =A56-WEEKDAY(A56,2)+1 | D56: =TEXT(A56,"mmm yyyy") | E56: Uit | F56: Checkify.pro Subs Fees | G56: Checkify.pro | H56: Software & Tools | I56: Zakelijk | J56: Nee | K56: 25.2
A57: 46188 | B57: =ISOWEEKNUM(A57) | C57: =A57-WEEKDAY(A57,2)+1 | D57: =TEXT(A57,"mmm yyyy") | E57: In | F57: Money added Stripe R2F5Z7 | G57: Stripe | H57: Omzet | I57: Zakelijk | J57: Nee | L57: 3049.48
A58: 46187 | B58: =ISOWEEKNUM(A58) | C58: =A58-WEEKDAY(A58,2)+1 | D58: =TEXT(A58,"mmm yyyy") | E58: Uit | F58: Shell Hilversum Nz Nl0720 | G58: Shell | H58: Brandstof | I58: Prive | J58: Ja | K58: 50
A59: 46187 | B59: =ISOWEEKNUM(A59) | C59: =A59-WEEKDAY(A59,2)+1 | D59: =TEXT(A59,"mmm yyyy") | E59: Uit | F59: Shell Haarrijn Nl 1390 | G59: Shell | H59: Brandstof | I59: Prive | J59: Ja | K59: 4.99
A60: 46187 | B60: =ISOWEEKNUM(A60) | C60: =A60-WEEKDAY(A60,2)+1 | D60: =TEXT(A60,"mmm yyyy") | E60: Uit | F60: Shell Station Ruwiel 0242 | G60: Shell | H60: Brandstof | I60: Prive | J60: Ja | K60: 6.73
A61: 46187 | B61: =ISOWEEKNUM(A61) | C61: =A61-WEEKDAY(A61,2)+1 | D61: =TEXT(A61,"mmm yyyy") | E61: Uit | F61: Kruidvat 7444 | G61: Kruidvat | H61: Persoonlijk | I61: Prive | J61: Ja | K61: 26.12 | N61: Drogist
A62: 46187 | B62: =ISOWEEKNUM(A62) | C62: =A62-WEEKDAY(A62,2)+1 | D62: =TEXT(A62,"mmm yyyy") | E62: Uit | F62: Easyparknlcom | G62: Easypark | H62: Parkeren | I62: Prive | J62: Ja | K62: 2.9
A63: 46187 | B63: =ISOWEEKNUM(A63) | C63: =A63-WEEKDAY(A63,2)+1 | D63: =TEXT(A63,"mmm yyyy") | E63: Uit | F63: Checkify.pro Subs Fees | G63: Checkify.pro | H63: Software & Tools | I63: Zakelijk | J63: Nee | K63: 25.25
A64: 46186 | B64: =ISOWEEKNUM(A64) | C64: =A64-WEEKDAY(A64,2)+1 | D64: =TEXT(A64,"mmm yyyy") | E64: Uit | F64: Shell Ruimteweg Nl 0601 | G64: Shell | H64: Brandstof | I64: Prive | J64: Ja | K64: 19.99
A65: 46186 | B65: =ISOWEEKNUM(A65) | C65: =A65-WEEKDAY(A65,2)+1 | D65: =TEXT(A65,"mmm yyyy") | E65: Uit | F65: Ccv snackline Gijsbrecht | G65: Snackline | H65: Eten & Restaurant | I65: Prive | J65: Ja | K65: 15
A66: 46186 | B66: =ISOWEEKNUM(A66) | C66: =A66-WEEKDAY(A66,2)+1 | D66: =TEXT(A66,"mmm yyyy") | E66: Uit | F66: Nimet Doner | G66: Nimet Doner | H66: Eten & Restaurant | I66: Prive | J66: Ja | K66: 15
A67: 46186 | B67: =ISOWEEKNUM(A67) | C67: =A67-WEEKDAY(A67,2)+1 | D67: =TEXT(A67,"mmm yyyy") | E67: Uit | F67: Easyparknlcom | G67: Easypark | H67: Parkeren | I67: Prive | J67: Ja | K67: 1.66
A68: 46185 | B68: =ISOWEEKNUM(A68) | C68: =A68-WEEKDAY(A68,2)+1 | D68: =TEXT(A68,"mmm yyyy") | E68: Uit | F68: To Talat Uyar Prive | G68: Talat (prive) | H68: Prive-opname | I68: Prive | J68: Ja | K68: 300 | N68: Opname naar prive
A69: 46185 | B69: =ISOWEEKNUM(A69) | C69: =A69-WEEKDAY(A69,2)+1 | D69: =TEXT(A69,"mmm yyyy") | E69: Uit | F69: Moonpay exodus 3882 | G69: Moonpay | H69: Crypto | I69: Prive | J69: Ja | K69: 52.13 | M69: $60.00 | N69: Crypto - verifieer
A70: 46185 | B70: =ISOWEEKNUM(A70) | C70: =A70-WEEKDAY(A70,2)+1 | D70: =TEXT(A70,"mmm yyyy") | E70: Uit | F70: Moonpay exodus 2327 | G70: Moonpay | H70: Crypto | I70: Prive | J70: Ja | K70: 95.4 | M70: $110.00 | N70: Crypto - verifieer
A71: 46185 | B71: =ISOWEEKNUM(A71) | C71: =A71-WEEKDAY(A71,2)+1 | D71: =TEXT(A71,"mmm yyyy") | E71: Uit | F71: Patreon Membership | G71: Patreon | H71: Persoonlijk | I71: Prive | J71: Ja | K71: 7.82 | M71: 33.28 PLN
A72: 46185 | B72: =ISOWEEKNUM(A72) | C72: =A72-WEEKDAY(A72,2)+1 | D72: =TEXT(A72,"mmm yyyy") | E72: Uit | F72: Esso Maartensdijk Ni | G72: Esso | H72: Brandstof | I72: Prive | J72: Ja | K72: 6.25
A73: 46185 | B73: =ISOWEEKNUM(A73) | C73: =A73-WEEKDAY(A73,2)+1 | D73: =TEXT(A73,"mmm yyyy") | E73: Uit | F73: Jumbo Larenseweg | G73: Jumbo | H73: Boodschappen | I73: Prive | J73: Ja | K73: 17.88
A74: 46185 | B74: =ISOWEEKNUM(A74) | C74: =A74-WEEKDAY(A74,2)+1 | D74: =TEXT(A74,"mmm yyyy") | E74: Uit | F74: Sumup arda S Barbers | G74: Barbier | H74: Persoonlijk | I74: Prive | J74: Ja | K74: 10 | N74: Kapper
A75: 46185 | B75: =ISOWEEKNUM(A75) | C75: =A75-WEEKDAY(A75,2)+1 | D75: =TEXT(A75,"mmm yyyy") | E75: Uit | F75: Checkify.pro Subs Fees | G75: Checkify.pro | H75: Software & Tools | I75: Zakelijk | J75: Nee | K75: 25.12
A76: 46185 | B76: =ISOWEEKNUM(A76) | C76: =A76-WEEKDAY(A76,2)+1 | D76: =TEXT(A76,"mmm yyyy") | E76: Uit | F76: To HK Jinchenyun CD000749 | G76: HK Jinchenyun | H76: Voorraad/Leverancier | I76: Zakelijk | J76: Nee | K76: 10000 | N76: Leverancier China
A77: 46185 | B77: =ISOWEEKNUM(A77) | C77: =A77-WEEKDAY(A77,2)+1 | D77: =TEXT(A77,"mmm yyyy") | E77: In | F77: Money added Stripe O9G9M2 | G77: Stripe | H77: Omzet | I77: Zakelijk | J77: Nee | L77: 2058.21
A78: 46185 | B78: =ISOWEEKNUM(A78) | C78: =A78-WEEKDAY(A78,2)+1 | D78: =TEXT(A78,"mmm yyyy") | E78: Uit | F78: To CC Ecommerce 0722 | G78: CC Ecommerce Solutions | H78: Voorraad/Leverancier | I78: Zakelijk | J78: Nee | K78: 4500
A79: 46184 | B79: =ISOWEEKNUM(A79) | C79: =A79-WEEKDAY(A79,2)+1 | D79: =TEXT(A79,"mmm yyyy") | E79: Uit | F79: Higgsfield Inc | G79: Higgsfield | H79: Software & Tools | I79: Zakelijk | J79: Nee | K79: 9.81
A80: 46184 | B80: =ISOWEEKNUM(A80) | C80: =A80-WEEKDAY(A80,2)+1 | D80: =TEXT(A80,"mmm yyyy") | E80: Uit | F80: Klaviyo Inc Software | G80: Klaviyo | H80: Software & Tools | I80: Zakelijk | J80: Nee | K80: 10.84 | M80: $12.50
A81: 46184 | B81: =ISOWEEKNUM(A81) | C81: =A81-WEEKDAY(A81,2)+1 | D81: =TEXT(A81,"mmm yyyy") | E81: Uit | F81: Moonpay exodus 7423 | G81: Moonpay | H81: Crypto | I81: Prive | J81: Ja | K81: 95.24 | M81: $110.00 | N81: Crypto - verifieer
A82: 46184 | B82: =ISOWEEKNUM(A82) | C82: =A82-WEEKDAY(A82,2)+1 | D82: =TEXT(A82,"mmm yyyy") | E82: Uit | F82: Moonpay exodus 3823 | G82: Moonpay | H82: Crypto | I82: Prive | J82: Ja | K82: 51.98 | M82: $60.00 | N82: Crypto - verifieer
A83: 46184 | B83: =ISOWEEKNUM(A83) | C83: =A83-WEEKDAY(A83,2)+1 | D83: =TEXT(A83,"mmm yyyy") | E83: Uit | F83: Moonpay exodus 9979 | G83: Moonpay | H83: Crypto | I83: Prive | J83: Ja | K83: 51.95 | M83: $60.00 | N83: Crypto - verifieer
A84: 46184 | B84: =ISOWEEKNUM(A84) | C84: =A84-WEEKDAY(A84,2)+1 | D84: =TEXT(A84,"mmm yyyy") | E84: Uit | F84: Shell Station Ruwiel 0242 | G84: Shell | H84: Brandstof | I84: Prive | J84: Ja | K84: 3.74
A85: 46184 | B85: =ISOWEEKNUM(A85) | C85: =A85-WEEKDAY(A85,2)+1 | D85: =TEXT(A85,"mmm yyyy") | E85: Uit | F85: Hetzner Online Gmbh | G85: Hetzner | H85: Software & Tools | I85: Zakelijk | J85: Nee | K85: 12.21 | N85: Server hosting
A86: 46184 | B86: =ISOWEEKNUM(A86) | C86: =A86-WEEKDAY(A86,2)+1 | D86: =TEXT(A86,"mmm yyyy") | E86: Uit | F86: Checkify.pro Subs Fees | G86: Checkify.pro | H86: Software & Tools | I86: Zakelijk | J86: Nee | K86: 25.17
A87: 46184 | B87: =ISOWEEKNUM(A87) | C87: =A87-WEEKDAY(A87,2)+1 | D87: =TEXT(A87,"mmm yyyy") | E87: In | F87: Money added Stripe H3M2P7 | G87: Stripe | H87: Omzet | I87: Zakelijk | J87: Nee | L87: 12610.1
A88: 46183 | B88: =ISOWEEKNUM(A88) | C88: =A88-WEEKDAY(A88,2)+1 | D88: =TEXT(A88,"mmm yyyy") | E88: Uit | F88: To CC Ecommerce 0722 | G88: CC Ecommerce Solutions | H88: Voorraad/Leverancier | I88: Zakelijk | J88: Nee | K88: 5000
A89: 46183 | B89: =ISOWEEKNUM(A89) | C89: =A89-WEEKDAY(A89,2)+1 | D89: =TEXT(A89,"mmm yyyy") | E89: Uit | F89: Paypal kuailuetwa4 | G89: PayPal | H89: Overig | I89: Zakelijk | J89: Nee | K89: 9.99 | N89: Check
A90: 46183 | B90: =ISOWEEKNUM(A90) | C90: =A90-WEEKDAY(A90,2)+1 | D90: =TEXT(A90,"mmm yyyy") | E90: Uit | F90: Higgsfield Inc | G90: Higgsfield | H90: Software & Tools | I90: Zakelijk | J90: Nee | K90: 58.25 | M90: $67.23
A91: 46183 | B91: =ISOWEEKNUM(A91) | C91: =A91-WEEKDAY(A91,2)+1 | D91: =TEXT(A91,"mmm yyyy") | E91: Uit | F91: Thuisbezorgd.nl | G91: Thuisbezorgd | H91: Eten & Restaurant | I91: Prive | J91: Ja | K91: 52.23
A92: 46183 | B92: =ISOWEEKNUM(A92) | C92: =A92-WEEKDAY(A92,2)+1 | D92: =TEXT(A92,"mmm yyyy") | E92: Uit | F92: Checkify.pro Subs Fees | G92: Checkify.pro | H92: Software & Tools | I92: Zakelijk | J92: Nee | K92: 25.06
A93: 46183 | B93: =ISOWEEKNUM(A93) | C93: =A93-WEEKDAY(A93,2)+1 | D93: =TEXT(A93,"mmm yyyy") | E93: In | F93: Money added Stripe V3A5E4 | G93: Stripe | H93: Omzet | I93: Zakelijk | J93: Nee | L93: 3641
A94: 46183 | B94: =ISOWEEKNUM(A94) | C94: =A94-WEEKDAY(A94,2)+1 | D94: =TEXT(A94,"mmm yyyy") | E94: Uit | F94: To HK Jinchenyun CD000749 | G94: HK Jinchenyun | H94: Voorraad/Leverancier | I94: Zakelijk | J94: Nee | K94: 2000
A95: 46182 | B95: =ISOWEEKNUM(A95) | C95: =A95-WEEKDAY(A95,2)+1 | D95: =TEXT(A95,"mmm yyyy") | E95: Uit | F95: Wetracked.io | G95: Wetracked | H95: Software & Tools | I95: Zakelijk | J95: Nee | K95: 94.47 | M95: $108.90 | N95: Tracking tool
A96: 46182 | B96: =ISOWEEKNUM(A96) | C96: =A96-WEEKDAY(A96,2)+1 | D96: =TEXT(A96,"mmm yyyy") | E96: Uit | F96: Vercel | G96: Vercel | H96: Software & Tools | I96: Zakelijk | J96: Nee | K96: 21.91 | M96: $25.26 | N96: Hosting
A97: 46182 | B97: =ISOWEEKNUM(A97) | C97: =A97-WEEKDAY(A97,2)+1 | D97: =TEXT(A97,"mmm yyyy") | E97: Uit | F97: Anthropic Claude Sub | G97: Anthropic | H97: Software & Tools | I97: Zakelijk | J97: Nee | K97: 108.9
A98: 46182 | B98: =ISOWEEKNUM(A98) | C98: =A98-WEEKDAY(A98,2)+1 | D98: =TEXT(A98,"mmm yyyy") | E98: Uit | F98: Texaco Maartensdijk | G98: Texaco | H98: Brandstof | I98: Prive | J98: Ja | K98: 22.19
A99: 46182 | B99: =ISOWEEKNUM(A99) | C99: =A99-WEEKDAY(A99,2)+1 | D99: =TEXT(A99,"mmm yyyy") | E99: Uit | F99: Shopify 541389840 | G99: Shopify | H99: Software & Tools | I99: Zakelijk | J99: Nee | K99: 92.15
A100: 46182 | B100: =ISOWEEKNUM(A100) | C100: =A100-WEEKDAY(A100,2)+1 | D100: =TEXT(A100,"mmm yyyy") | E100: Uit | F100: Dhgate.com | G100: DHgate | H100: Voorraad/Leverancier | I100: Zakelijk | J100: Nee | K100: 95.98 | N100: Inkoop/sample
...

Sheet Weekoverzicht
A1: Week | B1: Van (maandag) | C1: Inkomsten | D1: Uitgaven (totaal) | E1: waarvan zakelijk | F1: waarvan prive | G1: Netto
A2: Wk 20 | B2: 46153 | C2: =SUMIFS(Transacties!L:L,Transacties!C:C,B2) | D2: =SUMIFS(Transacties!K:K,Transacties!C:C,B2) | E2: =SUMIFS(Transacties!K:K,Transacties!C:C,B2,Transacties!I:I,"Zakelijk") | F2: =SUMIFS(Transacties!K:K,Transacties!C:C,B2,Transacties!I:I,"Prive") | G2: =C2-D2
A3: Wk 21 | B3: 46160 | C3: =SUMIFS(Transacties!L:L,Transacties!C:C,B3) | D3: =SUMIFS(Transacties!K:K,Transacties!C:C,B3) | E3: =SUMIFS(Transacties!K:K,Transacties!C:C,B3,Transacties!I:I,"Zakelijk") | F3: =SUMIFS(Transacties!K:K,Transacties!C:C,B3,Transacties!I:I,"Prive") | G3: =C3-D3
A4: Wk 22 | B4: 46167 | C4: =SUMIFS(Transacties!L:L,Transacties!C:C,B4) | D4: =SUMIFS(Transacties!K:K,Transacties!C:C,B4) | E4: =SUMIFS(Transacties!K:K,Transacties!C:C,B4,Transacties!I:I,"Zakelijk") | F4: =SUMIFS(Transacties!K:K,Transacties!C:C,B4,Transacties!I:I,"Prive") | G4: =C4-D4
A5: Wk 23 | B5: 46174 | C5: =SUMIFS(Transacties!L:L,Transacties!C:C,B5) | D5: =SUMIFS(Transacties!K:K,Transacties!C:C,B5) | E5: =SUMIFS(Transacties!K:K,Transacties!C:C,B5,Transacties!I:I,"Zakelijk") | F5: =SUMIFS(Transacties!K:K,Transacties!C:C,B5,Transacties!I:I,"Prive") | G5: =C5-D5
A6: Wk 24 | B6: 46181 | C6: =SUMIFS(Transacties!L:L,Transacties!C:C,B6) | D6: =SUMIFS(Transacties!K:K,Transacties!C:C,B6) | E6: =SUMIFS(Transacties!K:K,Transacties!C:C,B6,Transacties!I:I,"Zakelijk") | F6: =SUMIFS(Transacties!K:K,Transacties!C:C,B6,Transacties!I:I,"Prive") | G6: =C6-D6
A7: Wk 25 | B7: 46188 | C7: =SUMIFS(Transacties!L:L,Transacties!C:C,B7) | D7: =SUMIFS(Transacties!K:K,Transacties!C:C,B7) | E7: =SUMIFS(Transacties!K:K,Transacties!C:C,B7,Transacties!I:I,"Zakelijk") | F7: =SUMIFS(Transacties!K:K,Transacties!C:C,B7,Transacties!I:I,"Prive") | G7: =C7-D7
A8: Wk 26 | B8: 46195 | C8: =SUMIFS(Transacties!L:L,Transacties!C:C,B8) | D8: =SUMIFS(Transacties!K:K,Transacties!C:C,B8) | E8: =SUMIFS(Transacties!K:K,Transacties!C:C,B8,Transacties!I:I,"Zakelijk") | F8: =SUMIFS(Transacties!K:K,Transacties!C:C,B8,Transacties!I:I,"Prive") | G8: =C8-D8
A9: TOTAAL | C9: =SUM(C2:C8) | D9: =SUM(D2:D8) | E9: =SUM(E2:E8) | F9: =SUM(F2:F8) | G9: =SUM(G2:G8)

Sheet Categorieen
A1: Categorie | B1: Uitgaven (€) | C1: Inkomsten (€)
A2: Omzet | B2: =SUMIF(Transacties!H:H,A2,Transacties!K:K) | C2: =SUMIF(Transacties!H:H,A2,Transacties!L:L)
A3: Eigen inleg | B3: =SUMIF(Transacties!H:H,A3,Transacties!K:K) | C3: =SUMIF(Transacties!H:H,A3,Transacties!L:L)
A4: Voorraad/Leverancier | B4: =SUMIF(Transacties!H:H,A4,Transacties!K:K) | C4: =SUMIF(Transacties!H:H,A4,Transacties!L:L)
A5: Software & Tools | B5: =SUMIF(Transacties!H:H,A5,Transacties!K:K) | C5: =SUMIF(Transacties!H:H,A5,Transacties!L:L)
A6: Auto/Lease | B6: =SUMIF(Transacties!H:H,A6,Transacties!K:K) | C6: =SUMIF(Transacties!H:H,A6,Transacties!L:L)
A7: Brandstof | B7: =SUMIF(Transacties!H:H,A7,Transacties!K:K) | C7: =SUMIF(Transacties!H:H,A7,Transacties!L:L)
A8: Parkeren | B8: =SUMIF(Transacties!H:H,A8,Transacties!K:K) | C8: =SUMIF(Transacties!H:H,A8,Transacties!L:L)
A9: Boodschappen | B9: =SUMIF(Transacties!H:H,A9,Transacties!K:K) | C9: =SUMIF(Transacties!H:H,A9,Transacties!L:L)
A10: Eten & Restaurant | B10: =SUMIF(Transacties!H:H,A10,Transacties!K:K) | C10: =SUMIF(Transacties!H:H,A10,Transacties!L:L)
A11: Kleding | B11: =SUMIF(Transacties!H:H,A11,Transacties!K:K) | C11: =SUMIF(Transacties!H:H,A11,Transacties!L:L)
A12: Persoonlijk | B12: =SUMIF(Transacties!H:H,A12,Transacties!K:K) | C12: =SUMIF(Transacties!H:H,A12,Transacties!L:L)
A13: Crypto | B13: =SUMIF(Transacties!H:H,A13,Transacties!K:K) | C13: =SUMIF(Transacties!H:H,A13,Transacties!L:L)
... A17: Overig | B17: =SUMIF(Transacties!H:H,A17,Transacties!K:K) | C17: =SUMIF(Transacties!H:H,A17,Transacties!L:L)
A18: TOTAAL | B18: =SUM(B2:B17) | C18: =SUM(C2:C17)

Sheet Prive terugbetalen
A1: Prive terug te betalen aan het bedrijf
A2: Alles wat je prive met de zakelijke rekening betaalde (incl. brandstof + parkeren), plus opnames. Eigen inleg = al terugbetaald.
A4: Prive uitgaven + opnames (totaal) | B4: =SUMIF(Transacties!I:I,"Prive",Transacties!K:K)
A5: Al teruggestort (eigen inleg) | B5: =SUMIF(Transacties!H:H,"Eigen inleg",Transacties!L:L)
A6: NOG TERUG TE BETALEN | B6: =B4-B5
A8: Uitsplitsing prive per categorie
A9: Categorie | B9: Bedrag (€)
A10: Brandstof | B10: =SUMIFS(Transacties!K:K,Transacties!H:H,A10,Transacties!I:I,"Prive")
A11: Parkeren | B11: =SUMIFS(Transacties!K:K,Transacties!H:H,A11,Transacties!I:I,"Prive")
A12: Boodschappen | B12: =SUMIFS(Transacties!K:K,Transacties!H:H,A12,Transacties!I:I,"Prive")
A13: Eten & Restaurant | B13: =SUMIFS(Transacties!K:K,Transacties!H:H,A13,Transacties!I:I,"Prive")
A14: Kleding | B14: =SUMIFS(Transacties!K:K,Transacties!H:H,A14,Transacties!I:I,"Prive")
A15: Persoonlijk | B15: =SUMIFS(Transacties!K:K,Transacties!H:H,A15,Transacties!I:I,"Prive")
A16: Crypto | B16: =SUMIFS(Transacties!K:K,Transacties!H:H,A16,Transacties!I:I,"Prive")
A17: Auto/Lease | B17: =SUMIFS(Transacties!K:K,Transacties!H:H,A17,Transacties!I:I,"Prive")
A18: Prive-opname | B18: =SUMIFS(Transacties!K:K,Transacties!H:H,A18,Transacties!I:I,"Prive")
A19: Overig | B19: =SUMIFS(Transacties!K:K,Transacties!H:H,A19,Transacties!I:I,"Prive")
A20: TOTAAL prive | B20: =SUM(B10:B19)

Sheet Toelichting
A1: Cashflow-sheet Uyar Web & Trade — uitleg
A3: Wat dit is:
A4: Alle transacties op je Revolut Business rekening, 10 mei t/m 24 juni 2026 (Revolut account statement).
A5: Roze regel = prive, groene regel = geld erin. Klik de filterknoppen in de kop van 'Transacties' om te sorteren/filteren.
A7: De tabbladen:
A8: - Samenvatting: totalen + hoeveel je nog prive moet terugbetalen + controle tegen het Revolut-statement.
A9: - Transacties: alle regels met dropdowns (Categorie / Prive-Zakelijk / Terugbetalen).
A10: - Weekoverzicht: per week in / uit / netto, zakelijk vs prive (wk 20 t/m 26).
A11: - Categorieen: totaal per categorie.
A12: - Prive terugbetalen: wat je prive gebruikte minus je inleg.
A14: Wijziging t.o.v. vorige versie:
A15: Brandstof EN parkeren staan nu op PRIVE (jouw instructie). Ze tellen dus mee in 'nog terug te betalen'.
... A18: Prive uitgaven met de zakelijke kaart (boodschappen, eten, kleding, brandstof, parkeren, crypto) + opnames naar prive
A19: ='prive gebruikt'. Stortingen 'From Talat U' = 'eigen inleg' en halen dat van je schuld af.
A20: NOG TERUG TE BETALEN = prive gebruikt - eigen inleg. Dit is je rekening-courant met de zaak (check met boekhouder).
A22: Aannames (pas aan in kolom 'Prive/Zakelijk' als het anders is):
A23: - PRIVE: boodschappen, eten/restaurant, kleding, kapper, Kindle, Patreon, brandstof, parkeren, crypto (Moonpay).
A24: - ZAKELIJK: software/tools, leveranciers (CC Ecommerce, HK Jinchenyun, DHgate), bankkosten, telefoon.
A25: - Hiltermann Lease B.V. (1.779,50) = autolease, op ZAKELIJK gezet met de melding 'check prive/bijtelling'. Beoordeel zelf.
A26: - 'To Goatly VITAL NAD+' (23,97), Stichting Pair Finance (257), PayPal, 'To Koc via Tikkie', Merkala, MM Leidsche Rijn,
A27: Odido: gemarkeerd 'verifieer' in de notitie. Crypto staat op prive maar verifieer of het zakelijk is.
A29: Controle:
A30: Totaal uitgaven hoort 93.727,99 te zijn en inkomsten 102.382,04 (staat in het Revolut-statement). Klopt in de Samenvatting.
A32: Nieuwe maand toevoegen:
A33: Plak nieuwe regels onder in 'Transacties'. Datum + bedrag uit OF in invullen, dropdowns kiezen. Kolommen Week, Week-start
A34: en Maand vullen zichzelf (kopieer de formules mee uit de regel erboven). Alle totalen rekenen automatisch door.
A36: Grootste post: 'To CC Ecommerce Solutions 0722' (leverancier, dagelijks duizenden euro). Check tegen je inkoopfacturen.
